{
  "date": "2026-06-10",
  "universe_size": 30,
  "context_match_count": 9,
  "transition_match_count": 18,
  "full_match_count": 4,
  "context_classification": {
    "deep_drawdown": [
      "BRPT.JK",
      "TLKM.JK",
      "ASII.JK",
      "EXCL.JK",
      "MDKA.JK",
      "AMMN.JK",
      "TPIA.JK",
      "ANTM.JK",
      "ESSA.JK",
      "BBRI.JK",
      "BBCA.JK",
      "ICBP.JK",
      "INDF.JK",
      "GOTO.JK",
      "SIDO.JK",
      "CPIN.JK",
      "INTP.JK",
      "MIKA.JK",
      "KLBF.JK",
      "PGAS.JK",
      "UNTR.JK",
      "SMGR.JK",
      "HEAL.JK"
    ],
    "far_from_high": [
      "BRPT.JK",
      "TLKM.JK",
      "ASII.JK",
      "EXCL.JK",
      "MDKA.JK",
      "AMMN.JK",
      "TPIA.JK",
      "ANTM.JK",
      "ESSA.JK",
      "BBRI.JK",
      "BBCA.JK",
      "ICBP.JK",
      "INDF.JK",
      "GOTO.JK",
      "SIDO.JK",
      "CPIN.JK",
      "INTP.JK",
      "MIKA.JK",
      "KLBF.JK",
      "PGAS.JK",
      "ITMG.JK",
      "UNTR.JK",
      "SMGR.JK",
      "HEAL.JK"
    ],
    "high_volatility": [
      "BRPT.JK",
      "TLKM.JK",
      "ASII.JK",
      "EXCL.JK",
      "MDKA.JK",
      "AMMN.JK",
      "TPIA.JK",
      "ANTM.JK",
      "ESSA.JK",
      "MAPI.JK"
    ]
  },
  "signal_diagnostics": {
    "rs_change_60d_positive_count": 18,
    "volume_ratio_high_count": 8,
    "above_ma20_count": 5,
    "recovery_gt_10pct_count": 12,
    "avg_drawdown_252d": -34.59,
    "avg_volatility_60d": 3.35
  },
  "top_candidates": [
    {
      "ticker": "BRPT.JK",
      "drawdown": -57.24,
      "distance_from_high": -57.24,
      "volatility": 8.59,
      "rs_change_60d": 96.9,
      "volume_ratio": 1.39,
      "recovery": 46.4,
      "context_match": true,
      "transition_match": true,
      "full_match": true,
      "confirmation_count": 3
    },
    {
      "ticker": "TLKM.JK",
      "drawdown": -29.7,
      "distance_from_high": -29.7,
      "volatility": 3.49,
      "rs_change_60d": 21.5,
      "volume_ratio": 1.61,
      "recovery": 17.87,
      "context_match": true,
      "transition_match": true,
      "full_match": true,
      "confirmation_count": 2
    },
    {
      "ticker": "ASII.JK",
      "drawdown": -33.56,
      "distance_from_high": -33.56,
      "volatility": 3.4,
      "rs_change_60d": 11.23,
      "volume_ratio": 0.82,
      "recovery": 7.34,
      "context_match": true,
      "transition_match": true,
      "full_match": true,
      "confirmation_count": 0
    },
    {
      "ticker": "EXCL.JK",
      "drawdown": -42.76,
      "distance_from_high": -42.76,
      "volatility": 4.04,
      "rs_change_60d": 17.96,
      "volume_ratio": 0.84,
      "recovery": 5.33,
      "context_match": true,
      "transition_match": true,
      "full_match": true,
      "confirmation_count": 0
    },
    {
      "ticker": "MDKA.JK",
      "drawdown": -30.71,
      "distance_from_high": -30.71,
      "volatility": 5.4,
      "rs_change_60d": -51.77,
      "volume_ratio": 0.71,
      "recovery": 25.23,
      "context_match": true,
      "transition_match": false,
      "full_match": false,
      "confirmation_count": 2
    },
    {
      "ticker": "AMMN.JK",
      "drawdown": -61.48,
      "distance_from_high": -61.48,
      "volatility": 5.94,
      "rs_change_60d": -14.76,
      "volume_ratio": 0.61,
      "recovery": 16.9,
      "context_match": true,
      "transition_match": false,
      "full_match": false,
      "confirmation_count": 2
    },
    {
      "ticker": "TPIA.JK",
      "drawdown": -81.96,
      "distance_from_high": -81.96,
      "volatility": 8.8,
      "rs_change_60d": -27.34,
      "volume_ratio": 1.63,
      "recovery": 44.83,
      "context_match": true,
      "transition_match": false,
      "full_match": false,
      "confirmation_count": 2
    },
    {
      "ticker": "ANTM.JK",
      "drawdown": -38.45,
      "distance_from_high": -38.45,
      "volatility": 4.11,
      "rs_change_60d": -42.06,
      "volume_ratio": 1.3,
      "recovery": 15.81,
      "context_match": true,
      "transition_match": false,
      "full_match": false,
      "confirmation_count": 1
    },
    {
      "ticker": "ESSA.JK",
      "drawdown": -35.94,
      "distance_from_high": -35.94,
      "volatility": 4.31,
      "rs_change_60d": -17.62,
      "volume_ratio": 0.87,
      "recovery": 8.85,
      "context_match": true,
      "transition_match": false,
      "full_match": false,
      "confirmation_count": 0
    },
    {
      "ticker": "MAPI.JK",
      "drawdown": -1.0,
      "distance_from_high": -1.0,
      "volatility": 3.4,
      "rs_change_60d": 64.38,
      "volume_ratio": 1.03,
      "recovery": 37.96,
      "context_match": false,
      "transition_match": true,
      "full_match": false,
      "confirmation_count": 2
    }
  ]
}