{
    "last_update": "2026-06-09 20:18",
    "status": "SAFE",
    "market_health": 55,
    "opportunity": 65,
    "risk": 68,
    "confidence": 58,
    "capital_deployment": 58,
    "action": "ACCUMULATE",
    "rationale": "Divergensi pasar signifikan dengan score_gap 40.6, menunjukkan peluang selektif pada saham berkinerja tinggi namun risiko pada segmen lemah. Breadth pasar terpecah, dengan 7 saham kuat dan 7 saham lemah. Faktor Growth dominan (80), namun Quality terlemah (60), mengindikasikan potensi volatilitas. Dua dari lima saham watchlist menunjukkan lonjakan volume, menambah momentum sekaligus risiko. Meskipun score_gap_5d_change nol menunjukkan stabilitas divergensi, inkonsistensi data volume hari ini versus 5 hari terakhir memerlukan kehati-hatian. Keputusan ACCUMULATE didasarkan pada peluang spesifik dengan manajemen risiko ketat.",
    "detail_message": "Divergensi pasar signifikan dengan score_gap 40.6, menunjukkan peluang selektif pada saham berkinerja tinggi namun risiko pada segmen lemah. Breadth pasar terpecah, dengan 7 saham kuat dan 7 saham lemah. Faktor Growth dominan (80), namun Quality terlemah (60), mengindikasikan potensi volatilitas. Dua dari lima saham watchlist menunjukkan lonjakan volume, menambah momentum sekaligus risiko. Meskipun score_gap_5d_change nol menunjukkan stabilitas divergensi, inkonsistensi data volume hari ini versus 5 hari terakhir memerlukan kehati-hatian. Keputusan ACCUMULATE didasarkan pada peluang spesifik dengan manajemen risiko ketat.",
    "anomalies": [],
    "radar_context": {
        "production_config": "Config F",
        "top5_avg_score": 66.8,
        "bot5_avg_score": 26.2,
        "score_gap": 40.6,
        "score_gap_5d_change": 0,
        "breadth_above_70": 1,
        "breadth_above_60": 7,
        "breadth_below_40": 7,
        "strongest_factor": "Growth",
        "strongest_factor_score": 80.0,
        "weakest_factor": "Quality",
        "weakest_factor_score": 60.0,
        "top5_turnover": 0,
        "watchlist_count": 5
    },
    "volume_details": [
        "PTBA.JK: Volume 1.1x (Wajar)",
        "BBNI.JK: Volume 3.2x (Volume Lonjakan)",
        "INDF.JK: Volume 1.2x (Wajar)",
        "ASII.JK: Volume 1.0x (Wajar)",
        "ITMG.JK: Volume 2.8x (Volume Lonjakan)"
    ]
}