[
    {
        "ticker": "MAPI.JK",
        "return_12m": 1.2354,
        "rank": 1
    },
    {
        "ticker": "BMRI.JK",
        "return_12m": 0.4543,
        "rank": 2
    },
    {
        "ticker": "BBRI.JK",
        "return_12m": 0.3772,
        "rank": 3
    },
    {
        "ticker": "ICBP.JK",
        "return_12m": 0.3223,
        "rank": 4
    },
    {
        "ticker": "BBCA.JK",
        "return_12m": 0.2713,
        "rank": 5
    },
    {
        "ticker": "KLBF.JK",
        "return_12m": 0.2036,
        "rank": 6
    },
    {
        "ticker": "ASII.JK",
        "return_12m": 0.198,
        "rank": 7
    },
    {
        "ticker": "MIKA.JK",
        "return_12m": 0.1849,
        "rank": 8
    },
    {
        "ticker": "BBNI.JK",
        "return_12m": 0.1793,
        "rank": 9
    },
    {
        "ticker": "AKRA.JK",
        "return_12m": 0.1688,
        "rank": 10
    },
    {
        "ticker": "INDF.JK",
        "return_12m": 0.1625,
        "rank": 11
    },
    {
        "ticker": "INTP.JK",
        "return_12m": 0.1391,
        "rank": 12
    },
    {
        "ticker": "SMGR.JK",
        "return_12m": 0.1188,
        "rank": 13
    },
    {
        "ticker": "UNTR.JK",
        "return_12m": 0.0903,
        "rank": 14
    },
    {
        "ticker": "ANTM.JK",
        "return_12m": 0.0572,
        "rank": 15
    },
    {
        "ticker": "HEAL.JK",
        "return_12m": 0.0473,
        "rank": 16
    },
    {
        "ticker": "AMMN.JK",
        "return_12m": 0.0,
        "rank": 17
    },
    {
        "ticker": "EXCL.JK",
        "return_12m": -0.021,
        "rank": 18
    },
    {
        "ticker": "CPIN.JK",
        "return_12m": -0.0759,
        "rank": 19
    },
    {
        "ticker": "TLKM.JK",
        "return_12m": -0.0836,
        "rank": 20
    },
    {
        "ticker": "PTBA.JK",
        "return_12m": -0.0854,
        "rank": 21
    },
    {
        "ticker": "ITMG.JK",
        "return_12m": -0.0925,
        "rank": 22
    },
    {
        "ticker": "PGAS.JK",
        "return_12m": -0.0986,
        "rank": 23
    },
    {
        "ticker": "TPIA.JK",
        "return_12m": -0.1052,
        "rank": 24
    },
    {
        "ticker": "ADRO.JK",
        "return_12m": -0.1206,
        "rank": 25
    },
    {
        "ticker": "BRPT.JK",
        "return_12m": -0.1335,
        "rank": 26
    },
    {
        "ticker": "MDKA.JK",
        "return_12m": -0.1355,
        "rank": 27
    },
    {
        "ticker": "SIDO.JK",
        "return_12m": -0.2592,
        "rank": 28
    },
    {
        "ticker": "ESSA.JK",
        "return_12m": -0.4021,
        "rank": 29
    },
    {
        "ticker": "GOTO.JK",
        "return_12m": -0.6182,
        "rank": 30
    }
]