[
    {
        "ticker": "ADRO.JK",
        "return_12m": 0.5632,
        "rank": 1
    },
    {
        "ticker": "ARTO.JK",
        "return_12m": 0.5099,
        "rank": 2
    },
    {
        "ticker": "ACES.JK",
        "return_12m": 0.2764,
        "rank": 3
    },
    {
        "ticker": "PTBA.JK",
        "return_12m": 0.2728,
        "rank": 4
    },
    {
        "ticker": "BMRI.JK",
        "return_12m": 0.2082,
        "rank": 5
    },
    {
        "ticker": "BBCA.JK",
        "return_12m": 0.2026,
        "rank": 6
    },
    {
        "ticker": "PGAS.JK",
        "return_12m": 0.151,
        "rank": 7
    },
    {
        "ticker": "ICBP.JK",
        "return_12m": 0.1347,
        "rank": 8
    },
    {
        "ticker": "INDF.JK",
        "return_12m": 0.112,
        "rank": 9
    },
    {
        "ticker": "AKRA.JK",
        "return_12m": 0.107,
        "rank": 10
    },
    {
        "ticker": "BBNI.JK",
        "return_12m": 0.0858,
        "rank": 11
    },
    {
        "ticker": "AMRT.JK",
        "return_12m": 0.0783,
        "rank": 12
    },
    {
        "ticker": "UNTR.JK",
        "return_12m": 0.056,
        "rank": 13
    },
    {
        "ticker": "ITMG.JK",
        "return_12m": 0.022,
        "rank": 14
    },
    {
        "ticker": "KLBF.JK",
        "return_12m": 0.003,
        "rank": 15
    },
    {
        "ticker": "BBRI.JK",
        "return_12m": -0.0019,
        "rank": 16
    },
    {
        "ticker": "MDKA.JK",
        "return_12m": -0.0556,
        "rank": 17
    },
    {
        "ticker": "ASII.JK",
        "return_12m": -0.1008,
        "rank": 18
    },
    {
        "ticker": "CPIN.JK",
        "return_12m": -0.1122,
        "rank": 19
    },
    {
        "ticker": "ANTM.JK",
        "return_12m": -0.1162,
        "rank": 20
    },
    {
        "ticker": "TLKM.JK",
        "return_12m": -0.1539,
        "rank": 21
    },
    {
        "ticker": "PGEO.JK",
        "return_12m": -0.1817,
        "rank": 22
    },
    {
        "ticker": "MEDC.JK",
        "return_12m": -0.1864,
        "rank": 23
    },
    {
        "ticker": "BRPT.JK",
        "return_12m": -0.1903,
        "rank": 24
    },
    {
        "ticker": "GOTO.JK",
        "return_12m": -0.2235,
        "rank": 25
    },
    {
        "ticker": "INCO.JK",
        "return_12m": -0.2779,
        "rank": 26
    },
    {
        "ticker": "SMGR.JK",
        "return_12m": -0.3977,
        "rank": 27
    },
    {
        "ticker": "BUKA.JK",
        "return_12m": -0.445,
        "rank": 28
    }
]